README.md
fusionbuilder.py
setup.cfg
setup.py
fusionbuilder.egg-info/PKG-INFO
fusionbuilder.egg-info/SOURCES.txt
fusionbuilder.egg-info/dependency_links.txt
fusionbuilder.egg-info/requires.txt
fusionbuilder.egg-info/top_level.txt