Metadata-Version: 2.1
Name: fusionbuilder
Version: 0.0.1
Summary: Parse Fusion Page Builder text.
Home-page: https://github.com/edsu/fusionbuilder/
Author: Ed Summers
Author-email: ehs@pobox.com
License: UNKNOWN
Platform: UNKNOWN
